braintrust_api/__init__.py
braintrust_api/_base_client.py
braintrust_api/_client.py
braintrust_api/_compat.py
braintrust_api/_constants.py
braintrust_api/_exceptions.py
braintrust_api/_files.py
braintrust_api/_models.py
braintrust_api/_qs.py
braintrust_api/_resource.py
braintrust_api/_response.py
braintrust_api/_streaming.py
braintrust_api/_types.py
braintrust_api/_version.py
braintrust_api/pagination.py
braintrust_api/py.typed
braintrust_api/_utils/__init__.py
braintrust_api/_utils/_logs.py
braintrust_api/_utils/_proxy.py
braintrust_api/_utils/_reflection.py
braintrust_api/_utils/_streams.py
braintrust_api/_utils/_sync.py
braintrust_api/_utils/_transform.py
braintrust_api/_utils/_typing.py
braintrust_api/_utils/_utils.py
braintrust_api/lib/.keep
braintrust_api/resources/__init__.py
braintrust_api/resources/acls.py
braintrust_api/resources/ai_secrets.py
braintrust_api/resources/api_keys.py
braintrust_api/resources/datasets.py
braintrust_api/resources/env_vars.py
braintrust_api/resources/evals.py
braintrust_api/resources/experiments.py
braintrust_api/resources/functions.py
braintrust_api/resources/groups.py
braintrust_api/resources/project_scores.py
braintrust_api/resources/project_tags.py
braintrust_api/resources/prompts.py
braintrust_api/resources/roles.py
braintrust_api/resources/span_iframes.py
braintrust_api/resources/top_level.py
braintrust_api/resources/users.py
braintrust_api/resources/views.py
braintrust_api/resources/organizations/__init__.py
braintrust_api/resources/organizations/members.py
braintrust_api/resources/organizations/organizations.py
braintrust_api/resources/projects/__init__.py
braintrust_api/resources/projects/logs.py
braintrust_api/resources/projects/projects.py
braintrust_api/types/__init__.py
braintrust_api/types/acl_batch_update_params.py
braintrust_api/types/acl_create_params.py
braintrust_api/types/acl_find_and_delete_params.py
braintrust_api/types/acl_list_params.py
braintrust_api/types/ai_secret_create_params.py
braintrust_api-0.6.0.dist-info/METADATA
braintrust_api-0.6.0.dist-info/WHEEL
braintrust_api-0.6.0.dist-info/licenses/LICENSE
braintrust_api-0.6.0.dist-info/RECORD
